genebe/.gitignore
genebe/__init__.py
genebe/client.py
genebe/entrypoint.py
genebe/gbid.py
genebe/transcriptid.py
genebe/version.py
genebe-0.2.6.dist-info/METADATA
genebe-0.2.6.dist-info/WHEEL
genebe-0.2.6.dist-info/entry_points.txt
genebe-0.2.6.dist-info/top_level.txt
genebe-0.2.6.dist-info/RECORD
