Metadata-Version: 2.1
Name: genebe
Version: 0.2.6
Summary: GeneBe Client: A user-friendly system for annotating genetic variants
Author: Piotr Stawinski
Requires-Python: >=3.9
Requires-Dist: pymmh3
Requires-Dist: tinynetrc
Requires-Dist: pandas
Requires-Dist: requests
Requires-Dist: tqdm
Requires-Dist: jsonlines
Requires-Dist: numpy <2
Provides-Extra: cpp
Requires-Dist: mmh3 ; extra == 'cpp'
Provides-Extra: test
Requires-Dist: pytest >=6.0 ; extra == 'test'
Requires-Dist: pytest-cov ; extra == 'test'
Requires-Dist: pytest-mock ; extra == 'test'
Requires-Dist: coverage ; extra == 'test'
